LICENSE
README.md
setup.py
promptsec/__init__.py
promptsec/_common.py
promptsec_sdk.egg-info/PKG-INFO
promptsec_sdk.egg-info/SOURCES.txt
promptsec_sdk.egg-info/dependency_links.txt
promptsec_sdk.egg-info/requires.txt
promptsec_sdk.egg-info/top_level.txt